franklin/__init__.py
franklin/article.py
franklin/config.py
franklin/exceptions.py
franklin/fetch_doi.py
franklin/journals.py
franklin/orgmode.py
franklin/publishers.py
franklin/version.py
franklin-0.14.dist-info/LICENSE
franklin-0.14.dist-info/METADATA
franklin-0.14.dist-info/WHEEL
franklin-0.14.dist-info/entry_points.txt
franklin-0.14.dist-info/top_level.txt
franklin-0.14.dist-info/RECORD
