Metadata-Version: 2.1
Name: franklin
Version: 0.14
Summary: Retrieve scientific papers and manage associated citations.
Author-email: Mark Wolfman <wolfman@anl.gov>
Project-URL: Homepage, https://github.com/canismarko/franklin
Classifier: Development Status :: 2 - Pre-Alpha
Classifier: License :: OSI Approved :: GNU General Public License v3 (GPLv3)
Classifier: Programming Language :: Python :: 3
Classifier: Operating System :: OS Independent
Classifier: Topic :: Utilities
Classifier: Topic :: Scientific/Engineering
License-File: LICENSE
Requires-Dist: bibtexparser
Requires-Dist: requests
Requires-Dist: tqdm
Requires-Dist: pandas
Requires-Dist: titlecase
Requires-Dist: orgparse
Provides-Extra: dev
Requires-Dist: black ; extra == 'dev'
Requires-Dist: pytest ; extra == 'dev'
Requires-Dist: build ; extra == 'dev'
Requires-Dist: twine ; extra == 'dev'
Requires-Dist: flake8 ; extra == 'dev'
